strawchemy/__init__.py
strawchemy/config.py
strawchemy/constants.py
strawchemy/exceptions.py
strawchemy/graph.py
strawchemy/mapper.py
strawchemy/pydantic.py
strawchemy/types.py
strawchemy/typing.py
strawchemy/utils.py
strawchemy/dto/__init__.py
strawchemy/dto/base.py
strawchemy/dto/constants.py
strawchemy/dto/exceptions.py
strawchemy/dto/types.py
strawchemy/dto/utils.py
strawchemy/dto/backend/__init__.py
strawchemy/dto/backend/dataclass.py
strawchemy/dto/backend/pydantic.py
strawchemy/dto/factories/__init__.py
strawchemy/dto/factories/pydantic_sqlalchemy.py
strawchemy/dto/inspectors/__init__.py
strawchemy/dto/inspectors/sqlalchemy.py
strawchemy/graphql/__init__.py
strawchemy/graphql/constants.py
strawchemy/graphql/dto.py
strawchemy/graphql/exceptions.py
strawchemy/graphql/factory.py
strawchemy/graphql/inspector.py
strawchemy/graphql/typing.py
strawchemy/graphql/filters/__init__.py
strawchemy/graphql/filters/base.py
strawchemy/graphql/filters/geo.py
strawchemy/sqlalchemy/__init__.py
strawchemy/sqlalchemy/_executor.py
strawchemy/sqlalchemy/_query.py
strawchemy/sqlalchemy/_scope.py
strawchemy/sqlalchemy/_transpiler.py
strawchemy/sqlalchemy/exceptions.py
strawchemy/sqlalchemy/hook.py
strawchemy/sqlalchemy/inspector.py
strawchemy/sqlalchemy/typing.py
strawchemy/sqlalchemy/filters/__init__.py
strawchemy/sqlalchemy/filters/base.py
strawchemy/sqlalchemy/filters/geo.py
strawchemy/sqlalchemy/filters/postgresql.py
strawchemy/sqlalchemy/repository/__init__.py
strawchemy/sqlalchemy/repository/_async.py
strawchemy/sqlalchemy/repository/_base.py
strawchemy/sqlalchemy/repository/_sync.py
strawchemy/strawberry/__init__.py
strawchemy/strawberry/_field.py
strawchemy/strawberry/_instance.py
strawchemy/strawberry/_registry.py
strawchemy/strawberry/_utils.py
strawchemy/strawberry/exceptions.py
strawchemy/strawberry/factory.py
strawchemy/strawberry/geo.py
strawchemy/strawberry/inspector.py
strawchemy/strawberry/pydantic.py
strawchemy/strawberry/scalars.py
strawchemy/strawberry/typing.py
strawchemy-1.0.0.dist-info/METADATA
strawchemy-1.0.0.dist-info/WHEEL
strawchemy-1.0.0.dist-info/licenses/LICENCE
strawchemy-1.0.0.dist-info/RECORD
